lazy_github/__main__.py
lazy_github/cli.py
lazy_github/version.py
lazy_github/lib/bindings.py
lazy_github/lib/cache.py
lazy_github/lib/config.py
lazy_github/lib/constants.py
lazy_github/lib/context.py
lazy_github/lib/debug.py
lazy_github/lib/diff_parser.py
lazy_github/lib/git_cli.py
lazy_github/lib/logging.py
lazy_github/lib/messages.py
lazy_github/lib/github/auth.py
lazy_github/lib/github/branches.py
lazy_github/lib/github/checks.py
lazy_github/lib/github/client.py
lazy_github/lib/github/issues.py
lazy_github/lib/github/notifications.py
lazy_github/lib/github/pull_requests.py
lazy_github/lib/github/repositories.py
lazy_github/lib/github/users.py
lazy_github/lib/github/workflows.py
lazy_github/lib/github/backends/cli.py
lazy_github/lib/github/backends/hishel.py
lazy_github/lib/github/backends/protocol.py
lazy_github/models/github.py
lazy_github/ui/app.py
lazy_github/ui/screens/auth.py
lazy_github/ui/screens/confirm.py
lazy_github/ui/screens/create_or_edit_pull_request.py
lazy_github/ui/screens/debug.py
lazy_github/ui/screens/edit_issue.py
lazy_github/ui/screens/lookup_pull_request.py
lazy_github/ui/screens/lookup_repository.py
lazy_github/ui/screens/new_comment.py
lazy_github/ui/screens/new_issue.py
lazy_github/ui/screens/notifications.py
lazy_github/ui/screens/primary.py
lazy_github/ui/screens/settings.py
lazy_github/ui/screens/trigger_workflow.py
lazy_github/ui/widgets/command_log.py
lazy_github/ui/widgets/common.py
lazy_github/ui/widgets/conversations.py
lazy_github/ui/widgets/diff_viewer.py
lazy_github/ui/widgets/info.py
lazy_github/ui/widgets/issues.py
lazy_github/ui/widgets/pull_requests.py
lazy_github/ui/widgets/repositories.py
lazy_github/ui/widgets/split_diff_viewer.py
lazy_github/ui/widgets/workflow_run_details.py
lazy_github/ui/widgets/workflows.py
lazy_github-0.6.0.dist-info/METADATA
lazy_github-0.6.0.dist-info/WHEEL
lazy_github-0.6.0.dist-info/entry_points.txt
lazy_github-0.6.0.dist-info/licenses/LICENSE
lazy_github-0.6.0.dist-info/RECORD
