Metadata-Version: 2.4
Name: lazy-github
Version: 0.6.0
Summary: A terminal UI for interacting with Github
Author-email: "Chris (Gizmo)" <gizmo385@users.noreply.github.com>
Maintainer-email: "Chris (Gizmo)" <gizmo385@users.noreply.github.com>
License: MIT License
License-File: LICENSE
Classifier: Development Status :: 4 - Beta
Classifier: Intended Audience :: Developers
Classifier: License :: OSI Approved :: MIT License
Classifier: Programming Language :: Python :: 3.11
Requires-Python: >=3.11
Requires-Dist: click>=8.1.7
Requires-Dist: hishel<1.0.0
Requires-Dist: httpx
Requires-Dist: pydantic<3
Requires-Dist: textual
